{"stats":{"minecraft:picked_up":{"minecraft:waxed_copper_block":1,"minecraft:lantern":1,"minecraft:waxed_cut_copper_stairs":1},"minecraft:used":{"minecraft:shroomlight":9,"minecraft:red_shulker_box":25,"minecraft:netherite_block":65,"minecraft:iron_bars":4,"minecraft:chiseled_sandstone":9,"minecraft:flint_and_steel":4,"minecraft:red_concrete":157,"minecraft:spruce_slab":34,"minecraft:smooth_sandstone":575,"minecraft:oak_sign":1,"minecraft:smooth_sandstone_slab":81,"minecraft:spruce_planks":36,"minecraft:sandstone":20,"minecraft:stone":34,"minecraft:cut_sandstone":169,"minecraft:red_mushroom_block":19,"minecraft:redstone_block":11,"minecraft:sandstone_wall":50,"minecraft:smooth_sandstone_stairs":334,"minecraft:stone_bricks":9,"minecraft:netherrack":2,"minecraft:cracked_stone_bricks":1,"minecraft:debug_stick":43,"minecraft:diamond_block":38,"minecraft:red_carpet":156,"minecraft:orange_carpet":4,"minecraft:emerald_block":9,"minecraft:hopper":4,"minecraft:smooth_red_sandstone":52,"minecraft:lapis_block":17,"minecraft:gold_block":293,"minecraft:dripstone_block":1,"minecraft:stone_brick_wall":54},"minecraft:custom":{"minecraft:time_since_rest":165298,"minecraft:sprint_one_cm":24614,"minecraft:walk_one_cm":92250,"minecraft:fly_one_cm":1383718,"minecraft:crouch_one_cm":9934,"minecraft:open_shulker_box":1,"minecraft:play_time":165298,"minecraft:sneak_time":7340,"minecraft:walk_under_water_one_cm":1138,"minecraft:jump":178,"minecraft:leave_game":1,"minecraft:walk_on_water_one_cm":2230,"minecraft:time_since_death":165298,"minecraft:total_world_time":165298}},"DataVersion":3953}